<annotation>
	<folder></folder>
	<filename>China_Drone_000074_jpg.rf.45d806e1b4595371c94eb8a2d69f525b.jpg</filename>
	<path>China_Drone_000074_jpg.rf.45d806e1b4595371c94eb8a2d69f525b.jpg</path>
	<source>
		<database>roboflow.ai</database>
	</source>
	<size>
		<width>640</width>
		<height>640</height>
		<depth>3</depth>
	</size>
	<segmented>0</segmented>
	<object>
		<name>D00</name>
		<pose>Unspecified</pose>
		<truncated>0</truncated>
		<difficult>0</difficult>
		<occluded>0</occluded>
		<bndbox>
			<xmin>409</xmin>
			<xmax>473</xmax>
			<ymin>387</ymin>
			<ymax>610</ymax>
		</bndbox>
	</object>
	<object>
		<name>D10</name>
		<pose>Unspecified</pose>
		<truncated>0</truncated>
		<difficult>0</difficult>
		<occluded>0</occluded>
		<bndbox>
			<xmin>480</xmin>
			<xmax>641</xmax>
			<ymin>328</ymin>
			<ymax>388</ymax>
		</bndbox>
	</object>
</annotation>
